maxoptics/__init__.py
maxoptics/__main__.py
maxoptics/config.py
maxoptics/macros.py
maxoptics/maxopt_ofl.py
maxoptics/sdk.py
maxoptics/core/JSasync.py
maxoptics/core/TaskFile.py
maxoptics/core/__init__.py
maxoptics/core/abc.py
maxoptics/core/error.py
maxoptics/core/logger.py
maxoptics/core/base/BaseCell.py
maxoptics/core/base/BaseContainer.py
maxoptics/core/base/BaseDataCls.py
maxoptics/core/base/Runner.py
maxoptics/core/base/__init__.py
maxoptics/core/base/task.py
maxoptics/core/component/__init__.py
maxoptics/core/component/base/Attrs.py
maxoptics/core/component/base/Component.py
maxoptics/core/component/base/__init__.py
maxoptics/core/component/base/base.py
maxoptics/core/gdstools/GdsMaterial.py
maxoptics/core/gdstools/GdsParser.py
maxoptics/core/gdstools/GdsTypes.py
maxoptics/core/gdstools/PdkParser.py
maxoptics/core/gdstools/ProgressBar.py
maxoptics/core/gdstools/__init__.py
maxoptics/core/gdstools/structures.py
maxoptics/core/lonely/__init__.py
maxoptics/core/lonely/cross.py
maxoptics/core/lonely/dc.py
maxoptics/core/lonely/device.py
maxoptics/core/lonely/mmi12.py
maxoptics/core/lonely/mmi22.py
maxoptics/core/lonely/mzi.py
maxoptics/core/lonely/normal_band.py
maxoptics/core/lonely/reflector.py
maxoptics/core/lonely/reflector_mirror.py
maxoptics/core/lonely/ring.py
maxoptics/core/lonely/sdkbuild.py
maxoptics/core/lonely/si_transition.py
maxoptics/core/lonely/spliter.py
maxoptics/core/lonely/wg_transition.py
maxoptics/core/plot/GeoBase.py
maxoptics/core/plot/PolygonLike.py
maxoptics/core/plot/__init__.py
maxoptics/core/plot/draw_line.py
maxoptics/core/plot/draw_polygons.py
maxoptics/core/plot/heatmap.py
maxoptics/core/project/Project.py
maxoptics/core/project/ProjectBase.py
maxoptics/core/project/__init__.py
maxoptics/core/project/utils.py
maxoptics/core/utils/__init__.py
maxoptics/core/utils/attach_port.py
maxoptics/core/utils/currying.py
maxoptics/core/utils/configtools/__init__.py
maxoptics/core/utils/configtools/set.py
maxoptics-0.9.1.601.1236.dist-info/METADATA
maxoptics-0.9.1.601.1236.dist-info/WHEEL
maxoptics-0.9.1.601.1236.dist-info/top_level.txt
maxoptics-0.9.1.601.1236.dist-info/RECORD
