Metadata-Version: 2.1
Name: maxoptics
Version: 0.9.1.601.1236
Author: MaxOptics
Author-email: raojin@max-optics.com
Platform: any
Requires-Python: >=3.8
Requires-Dist: requests
Requires-Dist: matplotlib
Requires-Dist: numpy
Requires-Dist: pandas
Requires-Dist: pyyaml
Requires-Dist: gdspy
Requires-Dist: python-socketio
Requires-Dist: aiohttp
